{"bones": [{"name": "root"}, {"name": "bone", "parent": "root"}, {"name": "f", "parent": "root"}, {"scaleX": -1, "name": "f2", "parent": "root"}], "slots": [{"blend": "additive", "name": "hong_guang/hongguang_00000", "bone": "f"}, {"blend": "additive", "name": "hong_guang/hongguang_0", "bone": "f2"}, {"name": "hong/hongse_00000", "bone": "bone"}], "animations": {"zhuan": {"bones": {"f2": {"translate": [{"y": 135, "x": 0, "time": 0}]}, "root": {"translate": [{"y": -20.99, "x": 0, "time": 0}], "scale": [{"y": 0.983, "x": 0.933, "time": 0}]}, "bone": {"translate": [{"y": 137.81, "x": 0, "time": 0}]}, "f": {"translate": [{"y": 135, "x": 0, "time": 0}]}}, "slots": {"hong_guang/hongguang_0": {"attachment": [{"name": "hong_guang/hongguang_00000", "time": 0}, {"name": "hong_guang/hongguang_00002", "time": 0.0667}, {"name": "hong_guang/hongguang_00004", "time": 0.1333}, {"name": "hong_guang/hongguang_00006", "time": 0.2}, {"name": "hong_guang/hongguang_00008", "time": 0.2667}, {"name": "hong_guang/hongguang_00010", "time": 0.3333}, {"name": "hong_guang/hongguang_00012", "time": 0.4}, {"name": "hong_guang/hongguang_00014", "time": 0.4667}, {"name": "hong_guang/hongguang_00016", "time": 0.5333}, {"name": "hong_guang/hongguang_00018", "time": 0.6}, {"name": "hong_guang/hongguang_00020", "time": 0.6667}, {"name": "hong_guang/hongguang_00022", "time": 0.7333}, {"name": "hong_guang/hongguang_00024", "time": 0.8}, {"name": "hong_guang/hongguang_00026", "time": 0.8667}, {"name": "hong_guang/hongguang_00028", "time": 0.9333}, {"name": "hong_guang/hongguang_00030", "time": 1}, {"name": "hong_guang/hongguang_00032", "time": 1.0667}, {"name": "hong_guang/hongguang_00034", "time": 1.1333}, {"name": "hong_guang/hongguang_00036", "time": 1.2}, {"name": "hong_guang/hongguang_00038", "time": 1.2667}, {"name": "hong_guang/hongguang_00040", "time": 1.3333}]}, "hong_guang/hongguang_00000": {"attachment": [{"name": "hong_guang/hongguang_00000", "time": 0}, {"name": "hong_guang/hongguang_00002", "time": 0.0667}, {"name": "hong_guang/hongguang_00004", "time": 0.1333}, {"name": "hong_guang/hongguang_00006", "time": 0.2}, {"name": "hong_guang/hongguang_00008", "time": 0.2667}, {"name": "hong_guang/hongguang_00010", "time": 0.3333}, {"name": "hong_guang/hongguang_00012", "time": 0.4}, {"name": "hong_guang/hongguang_00014", "time": 0.4667}, {"name": "hong_guang/hongguang_00016", "time": 0.5333}, {"name": "hong_guang/hongguang_00018", "time": 0.6}, {"name": "hong_guang/hongguang_00020", "time": 0.6667}, {"name": "hong_guang/hongguang_00022", "time": 0.7333}, {"name": "hong_guang/hongguang_00024", "time": 0.8}, {"name": "hong_guang/hongguang_00026", "time": 0.8667}, {"name": "hong_guang/hongguang_00028", "time": 0.9333}, {"name": "hong_guang/hongguang_00030", "time": 1}, {"name": "hong_guang/hongguang_00032", "time": 1.0667}, {"name": "hong_guang/hongguang_00034", "time": 1.1333}, {"name": "hong_guang/hongguang_00036", "time": 1.2}, {"name": "hong_guang/hongguang_00038", "time": 1.2667}, {"name": "hong_guang/hongguang_00040", "time": 1.3333}]}, "hong/hongse_00000": {"attachment": [{"name": "hong/hongse_00000", "time": 0}, {"name": "hong/hongse_00002", "time": 0.0667}, {"name": "hong/hongse_00004", "time": 0.1333}, {"name": "hong/hongse_00006", "time": 0.2}, {"name": "hong/hongse_00008", "time": 0.2667}, {"name": "hong/hongse_00010", "time": 0.3333}, {"name": "hong/hongse_00012", "time": 0.4}, {"name": "hong/hongse_00014", "time": 0.4667}, {"name": "hong/hongse_00016", "time": 0.5333}, {"name": "hong/hongse_00018", "time": 0.6}, {"name": "hong/hongse_00020", "time": 0.6667}, {"name": "hong/hongse_00022", "time": 0.7333}, {"name": "hong/hongse_00024", "time": 0.8}, {"name": "hong/hongse_00026", "time": 0.8667}, {"name": "hong/hongse_00028", "time": 0.9333}, {"name": "hong/hongse_00030", "time": 1}, {"name": "hong/hongse_00032", "time": 1.0667}, {"name": "hong/hongse_00034", "time": 1.1333}, {"name": "hong/hongse_00036", "time": 1.2}, {"name": "hong/hongse_00038", "time": 1.2667}, {"name": "hong/hongse_00040", "time": 1.3333}]}}}}, "skeleton": {"spine": "3.6.53", "width": 0, "images": "./effect/", "hash": "6c6IX3ArroPxfrTb9PVH7FvammY", "height": 0}, "skins": {"default": {"hong_guang/hongguang_00000": {"hong_guang/hongguang_00018": {"width": 720, "height": 854}, "hong_guang/hongguang_00040": {"width": 720, "height": 854}, "hong_guang/hongguang_00008": {"width": 720, "height": 854}, "hong_guang/hongguang_00010": {"width": 720, "height": 854}, "hong_guang/hongguang_00006": {"width": 720, "height": 854}, "hong_guang/hongguang_00012": {"width": 720, "height": 854}, "hong_guang/hongguang_00004": {"width": 720, "height": 854}, "hong_guang/hongguang_00014": {"width": 720, "height": 854}, "hong_guang/hongguang_00002": {"width": 720, "height": 854}, "hong_guang/hongguang_00016": {"width": 720, "height": 854}, "hong_guang/hongguang_00000": {"width": 720, "height": 854}, "hong_guang/hongguang_00036": {"width": 720, "height": 854}, "hong_guang/hongguang_00024": {"width": 720, "height": 854}, "hong_guang/hongguang_00034": {"width": 720, "height": 854}, "hong_guang/hongguang_00026": {"width": 720, "height": 854}, "hong_guang/hongguang_00032": {"width": 720, "height": 854}, "hong_guang/hongguang_00020": {"width": 720, "height": 854}, "hong_guang/hongguang_00030": {"width": 720, "height": 854}, "hong_guang/hongguang_00022": {"width": 720, "height": 854}, "hong_guang/hongguang_00028": {"width": 720, "height": 854}, "hong_guang/hongguang_00038": {"width": 720, "height": 854}}, "hong_guang/hongguang_0": {"hong_guang/hongguang_00018": {"width": 720, "height": 854}, "hong_guang/hongguang_00040": {"width": 720, "height": 854}, "hong_guang/hongguang_00008": {"width": 720, "height": 854}, "hong_guang/hongguang_00010": {"width": 720, "height": 854}, "hong_guang/hongguang_00006": {"width": 720, "height": 854}, "hong_guang/hongguang_00012": {"width": 720, "height": 854}, "hong_guang/hongguang_00004": {"width": 720, "height": 854}, "hong_guang/hongguang_00014": {"width": 720, "height": 854}, "hong_guang/hongguang_00002": {"width": 720, "height": 854}, "hong_guang/hongguang_00016": {"width": 720, "height": 854}, "hong_guang/hongguang_00000": {"width": 720, "height": 854}, "hong_guang/hongguang_00036": {"width": 720, "height": 854}, "hong_guang/hongguang_00024": {"width": 720, "height": 854}, "hong_guang/hongguang_00034": {"width": 720, "height": 854}, "hong_guang/hongguang_00026": {"width": 720, "height": 854}, "hong_guang/hongguang_00032": {"width": 720, "height": 854}, "hong_guang/hongguang_00020": {"width": 720, "height": 854}, "hong_guang/hongguang_00030": {"width": 720, "height": 854}, "hong_guang/hongguang_00022": {"width": 720, "height": 854}, "hong_guang/hongguang_00028": {"width": 720, "height": 854}, "hong_guang/hongguang_00038": {"width": 720, "height": 854}}, "hong/hongse_00000": {"hong/hongse_00018": {"width": 720, "height": 854}, "hong/hongse_00006": {"width": 720, "height": 854}, "hong/hongse_00030": {"width": 720, "height": 854}, "hong/hongse_00004": {"width": 720, "height": 854}, "hong/hongse_00036": {"width": 720, "height": 854}, "hong/hongse_00002": {"width": 720, "height": 854}, "hong/hongse_00034": {"width": 720, "height": 854}, "hong/hongse_00000": {"width": 720, "height": 854}, "hong/hongse_00010": {"width": 720, "height": 854}, "hong/hongse_00028": {"width": 720, "height": 854}, "hong/hongse_00012": {"width": 720, "height": 854}, "hong/hongse_00026": {"width": 720, "height": 854}, "hong/hongse_00014": {"width": 720, "height": 854}, "hong/hongse_00016": {"width": 720, "height": 854}, "hong/hongse_00008": {"width": 720, "height": 854}, "hong/hongse_00022": {"width": 720, "height": 854}, "hong/hongse_00040": {"width": 720, "height": 854}, "hong/hongse_00020": {"width": 720, "height": 854}, "hong/hongse_00032": {"width": 720, "height": 854}, "hong/hongse_00038": {"width": 720, "height": 854}, "hong/hongse_00024": {"width": 720, "height": 854}}}}}