{"skeleton": {"hash": "p5mti4UnoWsy3KrwQcU0r2zh2Tk", "spine": "3.6.53", "height": 0, "width": 0, "fps": 15, "images": "./images/"}, "skins": {"default": {"dc/s_juqi/juqi_09": {"dc/s_juqi/juqi_27": {"width": 250, "height": 250}, "dc/s_juqi/juqi_13": {"width": 250, "height": 250}, "dc/s_juqi/juqi_25": {"width": 250, "height": 250}, "dc/s_juqi/juqi_11": {"width": 250, "height": 250}, "dc/s_juqi/juqi_17": {"width": 250, "height": 250}, "dc/s_juqi/juqi_21": {"width": 250, "height": 250}, "dc/s_juqi/juqi_09": {"width": 250, "height": 250}, "dc/s_juqi/juqi_19": {"width": 250, "height": 250}, "dc/s_juqi/juqi_29": {"width": 250, "height": 250}}, "dc/s_bo/daobo_25": {"dc/s_bo/daobo_39": {"width": 300, "height": 150}, "dc/s_bo/daobo_27": {"width": 300, "height": 150}, "dc/s_bo/daobo_25": {"width": 300, "height": 150}, "dc/s_bo/daobo_31": {"width": 300, "height": 150}, "dc/s_bo/daobo_33": {"width": 300, "height": 150}, "dc/s_bo/daobo_35": {"width": 300, "height": 150}, "dc/s_bo/daobo_37": {"width": 300, "height": 150}, "dc/s_bo/daobo_29": {"width": 300, "height": 150}}, "dc/s_dg/dg_25": {"dc/s_dg/dg_35": {"width": 220, "height": 160}, "dc/s_dg/dg_31": {"width": 220, "height": 160}, "dc/s_dg/dg_33": {"width": 220, "height": 160}, "dc/s_dg/dg_27": {"width": 220, "height": 160}, "dc/s_dg/dg_25": {"width": 220, "height": 160}, "dc/s_dg/dg_29": {"width": 220, "height": 160}}, "dc/a_dg/a_dg_20": {"dc/a_dg/a_dg_38": {"width": 200, "height": 200}, "dc/a_dg/a_dg_28": {"width": 200, "height": 200}, "dc/a_dg/a_dg_36": {"width": 200, "height": 200}, "dc/a_dg/a_dg_24": {"width": 200, "height": 200}, "dc/a_dg/a_dg_30": {"width": 200, "height": 200}, "dc/a_dg/a_dg_22": {"width": 200, "height": 200}, "dc/a_dg/a_dg_32": {"width": 200, "height": 200}, "dc/a_dg/a_dg_20": {"width": 200, "height": 200}}}}, "animations": {"attack": {"bones": {"attack_dg": {"translate": [{"y": 0, "x": 0, "time": 0}, {"y": 402.36, "x": 120.08, "curve": "stepped", "time": 0.6667}, {"y": 402.36, "x": 120.08, "time": 1.2}], "rotate": [{"curve": "stepped", "angle": 0, "time": 0}, {"angle": 0, "time": 1.2}], "scale": [{"y": 1, "x": 1, "time": 0}, {"y": 6, "x": 6, "curve": "stepped", "time": 0.6667}, {"y": 6, "x": 6, "time": 1.2}], "shear": [{"y": 0, "x": 0, "curve": "stepped", "time": 0}, {"y": 0, "x": 0, "time": 1.2}]}, "root": {"translate": [{"y": 0, "x": 0, "time": 0.8}], "rotate": [{"angle": 0, "time": 0.8}], "scale": [{"y": 0.801, "x": 0.801, "curve": "stepped", "time": 0}, {"y": 0.801, "x": 0.801, "time": 0.8}]}, "skill_juqi": {"translate": [{"y": 0, "x": 0, "curve": "stepped", "time": 0}, {"y": 0, "x": 0, "time": 1.2}], "rotate": [{"curve": "stepped", "angle": 0, "time": 0}, {"angle": 0, "time": 1.2}], "scale": [{"y": 1, "x": 1, "curve": "stepped", "time": 0}, {"y": 1, "x": 1, "time": 1.2}], "shear": [{"y": 0, "x": 0, "curve": "stepped", "time": 0}, {"y": 0, "x": 0, "time": 1.2}]}, "skill_dg": {"translate": [{"y": 0, "x": 0, "curve": "stepped", "time": 0}, {"y": 0, "x": 0, "time": 1.2}], "rotate": [{"curve": "stepped", "angle": 0, "time": 0}, {"angle": 0, "time": 1.2}], "scale": [{"y": 1, "x": 1, "curve": "stepped", "time": 0}, {"y": 1, "x": 1, "time": 1.2}], "shear": [{"y": 0, "x": 0, "curve": "stepped", "time": 0}, {"y": 0, "x": 0, "time": 1.2}]}}, "slots": {"dc/a_dg/a_dg_20": {"attachment": [{"name": "dc/a_dg/a_dg_20", "time": 0.6667}, {"name": "dc/a_dg/a_dg_22", "time": 0.7333}, {"name": "dc/a_dg/a_dg_24", "time": 0.8}, {"name": "dc/a_dg/a_dg_28", "time": 0.8667}, {"name": "dc/a_dg/a_dg_30", "time": 0.9333}, {"name": "dc/a_dg/a_dg_32", "time": 1}, {"name": "dc/a_dg/a_dg_36", "time": 1.0667}, {"name": "dc/a_dg/a_dg_38", "time": 1.1333}, {"name": null, "time": 1.2}]}}, "events": [{"name": "hit", "time": 0.6667}], "drawOrder": [{"time": 0.0667}, {"time": 0.5333}, {"time": 0.6667}]}, "skill": {"bones": {"skill_daobo": {"translate": [{"y": 316.39, "x": 527.32, "time": 0.8667}], "scale": [{"y": 6, "x": 6, "time": 0.8667}]}, "skill_dg": {"translate": [{"y": 355.55, "x": 100.07, "time": 0}, {"y": 407.98, "x": 100.07, "curve": "stepped", "time": 0.8}, {"y": 407.98, "x": 100.07, "time": 1.6}], "rotate": [{"curve": "stepped", "angle": 0, "time": 0}, {"angle": 0, "time": 1.6}], "scale": [{"y": 1, "x": 1, "time": 0}, {"y": 6, "x": 6, "curve": "stepped", "time": 0.8}, {"y": 6, "x": 6, "time": 1.6}], "shear": [{"y": 0, "x": 0, "curve": "stepped", "time": 0}, {"y": 0, "x": 0, "time": 1.6}]}, "root": {"scale": [{"y": 0.875, "x": 0.875, "time": 0}]}, "skill_juqi": {"translate": [{"y": 0, "x": 0, "time": 0}, {"y": 321.76, "x": 13.51, "curve": "stepped", "time": 0.2}, {"y": 321.76, "x": 13.51, "time": 1.6}], "rotate": [{"curve": "stepped", "angle": 0, "time": 0}, {"angle": 0, "time": 1.6}], "scale": [{"y": 1, "x": 1, "time": 0}, {"y": 4, "x": 4, "curve": "stepped", "time": 0.2}, {"y": 4, "x": 4, "time": 1.6}], "shear": [{"y": 0, "x": 0, "curve": "stepped", "time": 0}, {"y": 0, "x": 0, "time": 1.6}]}, "attack_dg": {"translate": [{"y": 0, "x": 0, "curve": "stepped", "time": 0}, {"y": 0, "x": 0, "time": 1.6}], "rotate": [{"curve": "stepped", "angle": 0, "time": 0}, {"angle": 0, "time": 1.6}], "scale": [{"y": 1, "x": 1, "curve": "stepped", "time": 0}, {"y": 1, "x": 1, "time": 1.6}], "shear": [{"y": 0, "x": 0, "curve": "stepped", "time": 0}, {"y": 0, "x": 0, "time": 1.6}]}}, "slots": {"dc/s_juqi/juqi_09": {"attachment": [{"name": "dc/s_juqi/juqi_09", "time": 0.2}, {"name": "dc/s_juqi/juqi_11", "time": 0.2667}, {"name": "dc/s_juqi/juqi_13", "time": 0.3333}, {"name": "dc/s_juqi/juqi_17", "time": 0.4}, {"name": "dc/s_juqi/juqi_19", "time": 0.4667}, {"name": "dc/s_juqi/juqi_21", "time": 0.5333}, {"name": "dc/s_juqi/juqi_25", "time": 0.6}, {"name": "dc/s_juqi/juqi_27", "time": 0.6667}, {"name": "dc/s_juqi/juqi_29", "time": 0.7333}, {"name": null, "time": 0.8}]}, "dc/s_bo/daobo_25": {"attachment": [{"name": "dc/s_bo/daobo_25", "time": 0.8667}, {"name": "dc/s_bo/daobo_27", "time": 0.9333}, {"name": "dc/s_bo/daobo_29", "time": 1}, {"name": "dc/s_bo/daobo_31", "time": 1.0667}, {"name": "dc/s_bo/daobo_33", "time": 1.1333}, {"name": "dc/s_bo/daobo_35", "time": 1.2}, {"name": "dc/s_bo/daobo_37", "time": 1.2667}, {"name": "dc/s_bo/daobo_39", "time": 1.3333}, {"name": null, "time": 1.4}]}, "dc/s_dg/dg_25": {"attachment": [{"name": "dc/s_dg/dg_25", "time": 0.8}, {"name": "dc/s_dg/dg_27", "time": 0.9333}, {"name": "dc/s_dg/dg_29", "time": 1.0667}, {"name": "dc/s_dg/dg_31", "time": 1.2}, {"name": "dc/s_dg/dg_33", "time": 1.3333}, {"name": "dc/s_dg/dg_35", "time": 1.4667}, {"name": null, "time": 1.6}]}}, "events": [{"name": "hit", "time": 0.8667}], "drawOrder": [{"time": 0.0667}, {"time": 0.8}]}}, "bones": [{"scaleX": 0.4, "name": "root", "scaleY": 0.4}, {"name": "attack_dg", "parent": "root"}, {"name": "skill_daobo", "parent": "root"}, {"name": "skill_dg", "parent": "root"}, {"name": "skill_juqi", "parent": "root"}], "slots": [{"name": "dc/a_dg/a_dg_20", "bone": "attack_dg"}, {"name": "dc/s_dg/dg_25", "bone": "skill_dg"}, {"name": "dc/s_juqi/juqi_09", "bone": "skill_juqi"}, {"name": "dc/s_bo/daobo_25", "bone": "skill_daobo"}], "events": {"hit": {}}}